HLR/__init__.py
HLR/diagnostic_tests.py
HLR/plots.py
HLR/regression.py
HLR-0.2.3.dist-info/AUTHORS.rst
HLR-0.2.3.dist-info/LICENSE
HLR-0.2.3.dist-info/METADATA
HLR-0.2.3.dist-info/WHEEL
HLR-0.2.3.dist-info/top_level.txt
HLR-0.2.3.dist-info/RECORD
