Metadata-Version: 2.1
Name: HLR
Version: 0.2.3
Summary: HLR - Hierarchical Linear Regression for Python
Home-page: https://github.com/teanijarv/HLR
Author: Toomas Erik Anijärv
Author-email: toomaserikanijarv@gmail.com
License: GNU General Public License v3
Keywords: HLR
Classifier: Development Status :: 2 - Pre-Alpha
Classifier: Intended Audience :: Developers
Classifier: License :: OSI Approved :: GNU General Public License v3 (GPLv3)
Classifier: Natural Language :: English
Classifier: Programming Language :: Python :: 3
Classifier: Programming Language :: Python :: 3.7
Classifier: Programming Language :: Python :: 3.8
Classifier: Programming Language :: Python :: 3.9
Requires-Python: >=3.9
License-File: LICENSE
License-File: AUTHORS.rst
Requires-Dist: scipy >=1.7.3
Requires-Dist: pandas >=1.3.5
Requires-Dist: matplotlib >=3.5.2
Requires-Dist: seaborn >=0.11
Requires-Dist: statsmodels >=0.13
Requires-Dist: pingouin >=0.5.3
